geonext/__init__.py
geonext/common.py
geonext/geonext.py
geonext-0.0.2.dist-info/licenses/LICENSE
geonext-0.0.2.dist-info/METADATA
geonext-0.0.2.dist-info/WHEEL
geonext-0.0.2.dist-info/entry_points.txt
geonext-0.0.2.dist-info/top_level.txt
geonext-0.0.2.dist-info/RECORD
