Metadata-Version: 2.4
Name: geonext
Version: 0.0.2
Summary: A Python package for geospatial analysis.
Author-email: Krishnagopal Halder <geonextgis@gmail.com>
License: MIT License
Project-URL: Homepage, https://github.com/geonextgis/geonext
Keywords: geonext
Classifier: Intended Audience :: Developers
Classifier: License :: OSI Approved :: MIT License
Classifier: Natural Language :: English
Classifier: Programming Language :: Python :: 3.8
Classifier: Programming Language :: Python :: 3.9
Classifier: Programming Language :: Python :: 3.10
Classifier: Programming Language :: Python :: 3.11
Classifier: Programming Language :: Python :: 3.12
Requires-Python: >=3.8
License-File: LICENSE
Requires-Dist: numpy
Provides-Extra: all
Requires-Dist: geonext[extra]; extra == "all"
Provides-Extra: extra
Requires-Dist: pandas; extra == "extra"
Dynamic: license-file
